poetry.lock
pureskillgg_datascience_showcase/__init__.py
pureskillgg_datascience_showcase/env_functions/env_setup.py
pureskillgg_datascience_showcase/notebook/__init__.py
pureskillgg_datascience_showcase/notebook/setup_notebook.py
pureskillgg_datascience_showcase/todo.py
pureskillgg_datascience_showcase/todo_test.py
pureskillgg_datascience_showcase-0.0.3.dist-info/LICENSE.txt
pureskillgg_datascience_showcase-0.0.3.dist-info/WHEEL
pureskillgg_datascience_showcase-0.0.3.dist-info/METADATA
pureskillgg_datascience_showcase-0.0.3.dist-info/RECORD
