Metadata-Version: 2.1
Name: pureskillgg-datascience-showcase
Version: 0.0.3
Summary: Showcase of public PureSkill.gg data set applications.
Home-page: https://github.com/pureskillgg/datascience-showcase
License: MIT
Author: PureSkill.gg
Author-email: contact@pureskill.gg
Requires-Python: >=3.9,<4.0
Classifier: License :: OSI Approved :: MIT License
Classifier: Programming Language :: Python :: 3
Classifier: Programming Language :: Python :: 3.10
Classifier: Programming Language :: Python :: 3.9
Requires-Dist: numpy (>=1.22.3,<2.0.0)
Requires-Dist: pandas (>=1.4.1,<2.0.0)
Requires-Dist: pureskillgg-csgo-dsdk (>=1.0.0b2,<2.0.0)
Requires-Dist: pureskillgg-dsdk (>=1.0.2b2,<2.0.0)
Requires-Dist: python-dotenv (>=0.20.0,<0.21.0)
Requires-Dist: requests (>=2.27.1,<3.0.0)
Project-URL: Repository, https://github.com/pureskillgg/datascience-showcase
